{"frames":{"fps-image9.png":{"frame":{"x":2,"y":2,"w":61,"h":65},"rotated":false,"trimmed":true,"spriteSourceSize":{"x":270,"y":110,"w":61,"h":65},"sourceSize":{"w":349,"h":259}},"fps-image8.png":{"frame":{"x":65,"y":2,"w":61,"h":65},"rotated":false,"trimmed":true,"spriteSourceSize":{"x":208,"y":110,"w":61,"h":65},"sourceSize":{"w":349,"h":259}},"fps-image7.png":{"frame":{"x":2,"y":69,"w":62,"h":65},"rotated":true,"trimmed":true,"spriteSourceSize":{"x":81,"y":110,"w":62,"h":65},"sourceSize":{"w":349,"h":259}},"fps-image6.png":{"frame":{"x":69,"y":69,"w":62,"h":65},"rotated":true,"trimmed":true,"spriteSourceSize":{"x":19,"y":110,"w":62,"h":65},"sourceSize":{"w":349,"h":259}},"fps-image5.png":{"frame":{"x":2,"y":133,"w":85,"h":88},"rotated":true,"trimmed":true,"spriteSourceSize":{"x":133,"y":97,"w":85,"h":88},"sourceSize":{"w":349,"h":259}},"fps-image4.png":{"frame":{"x":136,"y":2,"w":348,"h":259},"rotated":false,"trimmed":true,"spriteSourceSize":{"x":1,"y":0,"w":348,"h":259},"sourceSize":{"w":349,"h":259}},"fps-image3.png":{"frame":{"x":2,"y":263,"w":184,"h":559},"rotated":true,"trimmed":false,"spriteSourceSize":{"x":0,"y":0,"w":184,"h":559},"sourceSize":{"w":184,"h":559}},"fps-image20.png":{"frame":{"x":2,"y":449,"w":256,"h":512},"rotated":true,"trimmed":false,"spriteSourceSize":{"x":0,"y":0,"w":256,"h":512},"sourceSize":{"w":256,"h":512}},"fps-image2.png":{"frame":{"x":563,"y":2,"w":156,"h":153},"rotated":true,"trimmed":false,"spriteSourceSize":{"x":0,"y":0,"w":156,"h":153},"sourceSize":{"w":156,"h":153}},"fps-image19.png":{"frame":{"x":486,"y":160,"w":85,"h":87},"rotated":false,"trimmed":true,"spriteSourceSize":{"x":133,"y":248,"w":85,"h":87},"sourceSize":{"w":349,"h":410}},"fps-image18.png":{"frame":{"x":486,"y":2,"w":62,"h":65},"rotated":true,"trimmed":true,"spriteSourceSize":{"x":19,"y":260,"w":62,"h":65},"sourceSize":{"w":349,"h":410}},"fps-image17.png":{"frame":{"x":486,"y":66,"w":62,"h":64},"rotated":true,"trimmed":true,"spriteSourceSize":{"x":81,"y":261,"w":62,"h":64},"sourceSize":{"w":349,"h":410}},"fps-image16.png":{"frame":{"x":573,"y":160,"w":62,"h":65},"rotated":true,"trimmed":true,"spriteSourceSize":{"x":208,"y":261,"w":62,"h":65},"sourceSize":{"w":349,"h":410}},"fps-image15.png":{"frame":{"x":640,"y":160,"w":62,"h":66},"rotated":true,"trimmed":true,"spriteSourceSize":{"x":270,"y":260,"w":62,"h":66},"sourceSize":{"w":349,"h":410}},"fps-image14.png":{"frame":{"x":573,"y":224,"w":75,"h":51},"rotated":false,"trimmed":true,"spriteSourceSize":{"x":265,"y":149,"w":75,"h":51},"sourceSize":{"w":349,"h":410}},"fps-image12.png":{"frame":{"x":2,"y":707,"w":346,"h":409},"rotated":true,"trimmed":true,"spriteSourceSize":{"x":2,"y":0,"w":346,"h":409},"sourceSize":{"w":349,"h":410}},"fps-image10.png":{"frame":{"x":650,"y":224,"w":75,"h":49},"rotated":true,"trimmed":true,"spriteSourceSize":{"x":265,"y":0,"w":75,"h":49},"sourceSize":{"w":349,"h":259}},"fps-image1.png":{"frame":{"x":718,"y":2,"w":512,"h":508},"rotated":true,"trimmed":false,"spriteSourceSize":{"x":0,"y":0,"w":512,"h":508},"sourceSize":{"w":512,"h":508}}},"animations":{"fps-image":["fps-image1.png","fps-image2.png","fps-image3.png","fps-image4.png","fps-image5.png","fps-image6.png","fps-image7.png","fps-image8.png","fps-image9.png","fps-image10.png","fps-image12.png","fps-image14.png","fps-image15.png","fps-image16.png","fps-image17.png","fps-image18.png","fps-image19.png","fps-image20.png"]},"meta":{"app":"http://github.com/pixijs/assetpack","version":"1.0","image":"features-v9P9ow@0.5x.avif","format":"RGBA8888","size":{"w":1228,"h":1055},"scale":0.5,"related_multi_packs":[]}}