{"skeleton":{"hash":"+9fdzDUxUxkRiyGPF1ZbNN+syzI","spine":"3.7.94","width":821.34,"height":479.52,"images":"./images/","audio":""},"bones":[{"name":"root","scaleX":0.81,"scaleY":0.81},{"name":"reels","parent":"root"},{"name":"special_coin","parent":"root"},{"name":"10","parent":"root"},{"name":"bone","parent":"root"},{"name":"15","parent":"special_coin"},{"name":"mask","parent":"root"},{"name":"spin","parent":"mask"},{"name":"11","parent":"root"},{"name":"coin_4","parent":"spin"},{"name":"12","parent":"coin_4"},{"name":"coin_5","parent":"spin","x":12.95,"y":-5.18},{"name":"55","parent":"coin_5","x":-12.95,"y":5.18},{"name":"coin_6","parent":"spin"},{"name":"bone2","parent":"coin_6"},{"name":"coin_7","parent":"spin","x":12.95,"y":-5.18},{"name":"56","parent":"coin_7","x":-12.95,"y":5.18},{"name":"13","parent":"spin"},{"name":"14","parent":"spin"},{"name":"spin_2","parent":"mask"},{"name":"coin_10","parent":"spin_2"},{"name":"bone3","parent":"coin_10"},{"name":"coin_11","parent":"spin_2"},{"name":"bone4","parent":"coin_11"},{"name":"bone5","parent":"spin_2"},{"name":"coin_14","parent":"spin_2","x":12.95,"y":-5.18},{"name":"57","parent":"coin_14","x":-12.95,"y":5.18},{"name":"coin_15","parent":"spin_2"},{"name":"17","parent":"coin_15"},{"name":"coin_16","parent":"spin_2"},{"name":"18","parent":"coin_16"},{"name":"coin_17","parent":"spin_2","x":12.95,"y":-5.18},{"name":"58","parent":"coin_17","x":-12.95,"y":5.18},{"name":"coin_18","parent":"root"},{"name":"bone6","parent":"coin_18"},{"name":"coin_19","parent":"root"},{"name":"19","parent":"coin_19"},{"name":"coin_20","parent":"root"},{"name":"20","parent":"coin_20"},{"name":"21","parent":"root"},{"name":"coin_22","parent":"root"},{"name":"22","parent":"coin_22"},{"name":"bone7","parent":"root"},{"name":"coin_24","parent":"root"},{"name":"bone8","parent":"coin_24"},{"name":"coin_25","parent":"spin"},{"name":"23","parent":"coin_25"},{"name":"coin_26","parent":"spin"},{"name":"24","parent":"coin_26"},{"name":"coin_27","parent":"spin_2"},{"name":"bone9","parent":"coin_27"},{"name":"special_coin2","parent":"spin_2"},{"name":"186","parent":"special_coin2"},{"name":"16","parent":"root"}],"slots":[{"name":"reels_bonus_game","bone":"reels","attachment":"reels_bonus_game"},{"name":"special_coin","bone":"special_coin","color":"ffffff00","attachment":"special_coin"},{"name":"special_coin2","bone":"special_coin","color":"ffffff00","attachment":"special_coin","blend":"additive"},{"name":"coin19","bone":"coin_19","color":"ffffff00","attachment":"coin"},{"name":"19","bone":"19","color":"ffffff00","attachment":"7"},{"name":"coin24","bone":"coin_24","color":"ffffff00","attachment":"coin"},{"name":"mask","bone":"mask","attachment":"mask"},{"name":"coin27","bone":"coin_27","color":"ffffff00","attachment":"coin"},{"name":"major_stroke2","bone":"coin_27","color":"ffffff00","attachment":"major_stroke"},{"name":"special_coin3","bone":"special_coin2","color":"ffffff00","attachment":"special_coin"},{"name":"special_coin4","bone":"special_coin2","color":"ffffff00","attachment":"special_coin","blend":"additive"},{"name":"coin4","bone":"coin_4","color":"ffffff00","attachment":"coin"},{"name":"12","bone":"12","color":"ffffff00","attachment":"10"},{"name":"coin26","bone":"coin_26","color":"ffffff00","attachment":"coin"},{"name":"coin15","bone":"coin_15","color":"ffffff00","attachment":"coin"},{"name":"coin16","bone":"coin_16","color":"ffffff00","attachment":"coin"},{"name":"26","bone":"24","color":"ffffff00","attachment":"2"},{"name":"coin25","bone":"coin_25","color":"ffffff00","attachment":"coin"},{"name":"25","bone":"23","color":"ffffff00","attachment":"10"},{"name":"16","bone":"17","color":"ffffff00","attachment":"10"},{"name":"17","bone":"18","color":"ffffff00","attachment":"10"},{"name":"24","bone":"bone8","color":"ffffff00","attachment":"2"},{"name":"major5","bone":"bone9","color":"ffffff00","attachment":"major"},{"name":"major4","bone":"bone5","color":"ffffff00","attachment":"major"},{"name":"15_collect","bone":"15","color":"ffffff00","attachment":"15_collect"},{"name":"15_collect2","bone":"16","color":"ffffff00","attachment":"15_collect"},{"name":"coin5","bone":"coin_5","color":"ffffff00","attachment":"coin"},{"name":"coin14","bone":"coin_14","color":"ffffff00","attachment":"coin"},{"name":"coin17","bone":"coin_17","color":"ffffff00","attachment":"coin"},{"name":"coin7","bone":"coin_7","color":"ffffff00","attachment":"coin"},{"name":"6","bone":"55","color":"ffffff00","attachment":"5"},{"name":"8","bone":"57","color":"ffffff00","attachment":"5"},{"name":"9","bone":"58","color":"ffffff00","attachment":"5"},{"name":"7","bone":"56","color":"ffffff00","attachment":"5"},{"name":"coin6","bone":"coin_6","color":"ffffff00","attachment":"coin"},{"name":"coin10","bone":"coin_10","color":"ffffff00","attachment":"coin"},{"name":"coin11","bone":"coin_11","color":"ffffff00","attachment":"coin"},{"name":"major","bone":"bone2","color":"ffffff00","attachment":"major"},{"name":"major2","bone":"bone3","color":"ffffff00","attachment":"major"},{"name":"major3","bone":"bone4","color":"ffffff00","attachment":"major"},{"name":"coin22","bone":"coin_22","color":"ffffff00","attachment":"coin"},{"name":"22","bone":"22","color":"ffffff00","attachment":"5"},{"name":"coin20","bone":"coin_20","color":"ffffff00","attachment":"coin"},{"name":"20","bone":"20","color":"ffffff00","attachment":"2"},{"name":"186","bone":"186","color":"ffffff00","attachment":"370_collect"},{"name":"coin18","bone":"coin_18","color":"ffffff00","attachment":"coin"},{"name":"18","bone":"bone6","color":"ffffff00","attachment":"2"},{"name":"10","bone":"10","color":"ffffff00","attachment":"7"},{"name":"21","bone":"21","color":"ffffff00","attachment":"5"},{"name":"11","bone":"11","color":"ffffff00","attachment":"2"},{"name":"23","bone":"bone7","color":"ffffff00","attachment":"2"},{"name":"14","bone":"14","color":"ffffff00","attachment":"2"},{"name":"13","bone":"13","color":"ffffff00","attachment":"10"},{"name":"5","bone":"bone","color":"ffffff00","attachment":"2"}],"skins":{"default":{"10":{"7":{"width":126,"height":52}},"11":{"2":{"width":126,"height":52}},"12":{"10":{"width":134,"height":52}},"13":{"10":{"width":134,"height":52}},"14":{"2":{"width":126,"height":52}},"15_collect":{"15_collect":{"width":172,"height":66}},"15_collect2":{"15_collect":{"width":172,"height":66}},"16":{"10":{"width":134,"height":52}},"17":{"10":{"width":134,"height":52}},"18":{"2":{"x":0.5,"width":126,"height":52}},"186":{"370_collect":{"x":0.5,"y":0.5,"width":222,"height":73}},"19":{"7":{"width":126,"height":52}},"20":{"2":{"width":126,"height":52}},"21":{"5":{"width":126,"height":52}},"22":{"5":{"width":126,"height":52}},"23":{"2":{"x":0.5,"width":126,"height":52}},"24":{"2":{"x":0.5,"width":126,"height":52}},"25":{"10":{"width":134,"height":52}},"26":{"2":{"width":126,"height":52}},"5":{"2":{"x":0.5,"width":126,"height":52}},"6":{"5":{"x":0.5,"width":126,"height":52}},"7":{"5":{"x":0.5,"width":126,"height":52}},"8":{"5":{"x":0.5,"width":126,"height":52}},"9":{"5":{"x":0.5,"width":126,"height":52}},"coin10":{"coin":{"y":0.5,"width":188,"height":187}},"coin11":{"coin":{"y":0.5,"width":188,"height":187}},"coin14":{"coin":{"y":0.5,"width":188,"height":187}},"coin15":{"coin":{"y":0.5,"width":188,"height":187}},"coin16":{"coin":{"y":0.5,"width":188,"height":187}},"coin17":{"coin":{"y":0.5,"width":188,"height":187}},"coin18":{"coin":{"y":0.5,"width":188,"height":187}},"coin19":{"coin":{"y":0.5,"width":188,"height":187}},"coin20":{"coin":{"y":0.5,"width":188,"height":187}},"coin22":{"coin":{"y":0.5,"width":188,"height":187}},"coin24":{"coin":{"y":0.5,"width":188,"height":187}},"coin25":{"coin":{"y":0.5,"width":188,"height":187}},"coin26":{"coin":{"y":0.5,"width":188,"height":187}},"coin27":{"coin":{"y":0.5,"width":188,"height":187}},"coin4":{"coin":{"y":0.5,"width":188,"height":187}},"coin5":{"coin":{"y":0.5,"width":188,"height":187}},"coin6":{"coin":{"y":0.5,"width":188,"height":187}},"coin7":{"coin":{"y":0.5,"width":188,"height":187}},"major":{"major":{"width":226,"height":84}},"major2":{"major":{"width":226,"height":84}},"major3":{"major":{"width":226,"height":84}},"major4":{"major":{"width":226,"height":84}},"major5":{"major":{"width":226,"height":84}},"major_stroke2":{"major_stroke":{"y":1,"scaleX":0.82,"scaleY":0.82,"width":288,"height":276}},"mask":{"mask":{"type":"clipping","end":"major3","vertexCount":4,"vertices":[-455.95,-235.1,-459.14,244.7,458.75,246.64,456.99,-235.67],"color":"ce3a3aff"}},"reels_bonus_game":{"reels_bonus_game":{"width":1014,"height":592}},"special_coin":{"special_coin":{"width":268,"height":268}},"special_coin2":{"special_coin":{"width":268,"height":268}},"special_coin3":{"special_coin":{"width":268,"height":268}},"special_coin4":{"special_coin":{"width":268,"height":268}}}},"animations":{"animation":{"slots":{"10":{"color":[{"time":0,"color":"ffffff00","curve":"stepped"},{"time":0.2333,"color":"ffffffff","curve":"stepped"},{"time":0.5667,"color":"ffffffff"},{"time":0.6667,"color":"ffffff00","curve":"stepped"},{"time":2.2667,"color":"ffffffff","curve":"stepped"},{"time":2.6,"color":"ffffffff"},{"time":2.7333,"color":"ffffff00"}],"attachment":[{"time":3.4667,"name":null}]},"11":{"color":[{"time":0,"color":"ffffffff","curve":"stepped"},{"time":0.3333,"color":"ffffffff"},{"time":0.4667,"color":"ffffff00","curve":"stepped"},{"time":2,"color":"ffffffff","curve":"stepped"},{"time":2.3333,"color":"ffffffff"},{"time":2.4667,"color":"ffffff00"}]},"12":{"color":[{"time":0,"color":"ffffffff"}]},"13":{"color":[{"time":0,"color":"ffffff00","curve":"stepped"},{"time":2.1333,"color":"ffffffff","curve":"stepped"},{"time":2.4667,"color":"ffffffff"},{"time":2.6,"color":"ffffff00"}]},"14":{"color":[{"time":0,"color":"ffffff00","curve":"stepped"},{"time":2.0667,"color":"ffffffff","curve":"stepped"},{"time":2.4,"color":"ffffffff"},{"time":2.5333,"color":"ffffff00"}]},"15_collect":{"color":[{"time":0,"color":"ffffff00","curve":"stepped"},{"time":0.7667,"color":"ffffff00","curve":[0.25,0,0.255,1]},{"time":0.9,"color":"ffffffff","curve":"stepped"},{"time":4.8333,"color":"ffffffff"},{"time":5.2333,"color":"ffffff00"}]},"16":{"color":[{"time":0,"color":"ffffffff"}]},"17":{"color":[{"time":0,"color":"ffffffff"}]},"18":{"color":[{"time":0,"color":"ffffffff"}]},"19":{"color":[{"time":0,"color":"ffffffff"}]},"186":{"color":[{"time":0,"color":"ffffff00","curve":"stepped"},{"time":3.0667,"color":"ffffff00","curve":[0.25,0,0.75,1]},{"time":3.2,"color":"ffffffff","curve":"stepped"},{"time":4.8333,"color":"ffffffff"},{"time":5.1,"color":"ffffff00"}]},"15_collect2":{"color":[{"time":0,"color":"ffffff00","curve":"stepped"},{"time":2.4,"color":"ffffffff","curve":"stepped"},{"time":2.7333,"color":"ffffffff"},{"time":2.8667,"color":"ffffff00"}]},"20":{"color":[{"time":0,"color":"ffffffff"}]},"21":{"color":[{"time":0,"color":"ffffff00","curve":"stepped"},{"time":0.1333,"color":"ffffffff","curve":"stepped"},{"time":0.4667,"color":"ffffffff"},{"time":0.6,"color":"ffffff00","curve":"stepped"},{"time":2.2,"color":"ffffffff","curve":"stepped"},{"time":2.5333,"color":"ffffffff"},{"time":2.6667,"color":"ffffff00"}],"attachment":[{"time":0,"name":"5"}]},"22":{"color":[{"time":0,"color":"ffffffff"}]},"23":{"color":[{"time":0,"color":"ffffff00","curve":"stepped"},{"time":0.4333,"color":"ffffffff","curve":"stepped"},{"time":0.7667,"color":"ffffffff"},{"time":0.8333,"color":"ffffff00","curve":"stepped"},{"time":2.7333,"color":"ffffffff","curve":"stepped"},{"time":3.0667,"color":"ffffffff"},{"time":3.2,"color":"ffffff00"}]},"24":{"color":[{"time":0,"color":"ffffffff"}]},"25":{"color":[{"time":0,"color":"ffffffff","curve":"stepped"},{"time":4.8333,"color":"ffffffff"},{"time":5.1,"color":"ffffff00"}]},"26":{"color":[{"time":0,"color":"ffffffff","curve":"stepped"},{"time":4.8333,"color":"ffffffff"},{"time":5.1,"color":"ffffff00"}]},"5":{"color":[{"time":0,"color":"ffffff00","curve":"stepped"},{"time":0.3333,"color":"ffffffff","curve":"stepped"},{"time":0.6667,"color":"ffffffff"},{"time":0.7667,"color":"ffffff00","curve":"stepped"},{"time":2.5333,"color":"ffffffff","curve":"stepped"},{"time":2.8667,"color":"ffffffff"},{"time":3,"color":"ffffff00"}]},"6":{"color":[{"time":0,"color":"ffffffff"}]},"7":{"color":[{"time":0,"color":"ffffffff"}]},"8":{"color":[{"time":0,"color":"ffffffff"}]},"9":{"color":[{"time":0,"color":"ffffffff"}]},"coin4":{"color":[{"time":0,"color":"ffffffff"}]},"coin5":{"color":[{"time":0,"color":"ffffffff"}]},"coin6":{"color":[{"time":0,"color":"ffffffff"}]},"coin7":{"color":[{"time":0,"color":"ffffffff"}]},"coin10":{"color":[{"time":0,"color":"ffffffff"}]},"coin11":{"color":[{"time":0,"color":"ffffffff"}]},"coin14":{"color":[{"time":0,"color":"ffffffff"}]},"coin15":{"color":[{"time":0,"color":"ffffffff"}]},"coin16":{"color":[{"time":0,"color":"ffffffff"}]},"coin17":{"color":[{"time":0,"color":"ffffffff"}]},"coin18":{"color":[{"time":0,"color":"ffffffff"}],"attachment":[{"time":0,"name":"coin"}]},"coin19":{"color":[{"time":0,"color":"ffffffff"}]},"coin20":{"color":[{"time":0,"color":"ffffffff"}],"attachment":[{"time":0,"name":"coin"}]},"coin22":{"color":[{"time":0,"color":"ffffffff"}],"attachment":[{"time":0,"name":"coin"}]},"coin24":{"color":[{"time":0,"color":"ffffffff"}],"attachment":[{"time":0,"name":"coin"}]},"coin25":{"color":[{"time":0,"color":"ffffffff","curve":"stepped"},{"time":4.8333,"color":"ffffffff"},{"time":5.1,"color":"ffffff00"}]},"coin26":{"color":[{"time":0,"color":"ffffffff","curve":"stepped"},{"time":4.9667,"color":"ffffffff"},{"time":5.3333,"color":"ffffff00"}]},"coin27":{"color":[{"time":0,"color":"ffffffff","curve":"stepped"},{"time":4.8333,"color":"ffffffff"},{"time":5.1,"color":"ffffff00"}],"attachment":[{"time":0,"name":"coin"}]},"major":{"color":[{"time":0,"color":"ffffffff"}]},"major2":{"color":[{"time":0,"color":"ffffffff"}]},"major3":{"color":[{"time":0,"color":"ffffffff"}]},"major4":{"color":[{"time":0,"color":"ffffff00","curve":"stepped"},{"time":2.6333,"color":"ffffffff","curve":"stepped"},{"time":2.9667,"color":"ffffffff"},{"time":3.1,"color":"ffffff00"}],"attachment":[{"time":0,"name":"major"},{"time":2.6333,"name":"major"}]},"major5":{"color":[{"time":0,"color":"ffffffff","curve":"stepped"},{"time":4.8333,"color":"ffffffff"},{"time":5.1,"color":"ffffff00"}],"attachment":[{"time":0,"name":"major"}]},"major_stroke2":{"color":[{"time":0,"color":"ffffffff","curve":"stepped"},{"time":4.8333,"color":"ffffffff"},{"time":5.1,"color":"ffffff00"}],"attachment":[{"time":0,"name":"major_stroke"}]},"reels_bonus_game":{"color":[{"time":0,"color":"ffffffff"}]},"special_coin":{"color":[{"time":0,"color":"ffffffff"}]},"special_coin2":{"color":[{"time":0,"color":"ffffff00","curve":"stepped"},{"time":0.3667,"color":"ffffff00","curve":[0.25,0,0.75,1]},{"time":0.4333,"color":"ffffff4c","curve":[0.25,0,0.75,1]},{"time":0.6,"color":"ffffff00","curve":"stepped"},{"time":0.7667,"color":"ffffff00"},{"time":0.9,"color":"ffffff4c"},{"time":1.2,"color":"ffffff00"}]},"special_coin3":{"color":[{"time":0,"color":"ffffffff","curve":"stepped"},{"time":4.8333,"color":"ffffffff"},{"time":5.1,"color":"ffffff00"}]},"special_coin4":{"color":[{"time":0,"color":"ffffff00","curve":"stepped"},{"time":3.0667,"color":"ffffff00"},{"time":3.1667,"color":"ffffff4c"},{"time":3.5,"color":"ffffff00"}]}},"bones":{"special_coin":{"translate":[{"time":0,"x":0,"y":0}],"scale":[{"time":0,"x":1,"y":1,"curve":"stepped"},{"time":0.7667,"x":1,"y":1,"curve":[0.25,0,0.346,0.99]},{"time":0.9,"x":1.13,"y":1.13,"curve":[0.25,0,0.33,0.99]},{"time":1.2,"x":1,"y":1,"curve":"stepped"},{"time":2.3667,"x":1,"y":1,"curve":[0.25,0,0.75,1]},{"time":2.4333,"x":1.06,"y":1.06,"curve":[0.25,0,0.75,1]},{"time":2.5333,"x":1,"y":1}]},"10":{"translate":[{"time":0,"x":-176,"y":-158.02,"curve":"stepped"},{"time":0.2333,"x":-176,"y":-158.02,"curve":[0.25,0,0.75,1]},{"time":0.5667,"x":0,"y":0,"curve":"stepped"},{"time":2.2667,"x":-176,"y":-158.02,"curve":[0.25,0,0.75,1]},{"time":2.6,"x":172,"y":-163}]},"bone":{"translate":[{"time":0,"x":172,"y":167,"curve":"stepped"},{"time":0.3333,"x":172,"y":167,"curve":[0.25,0,0.75,1]},{"time":0.6667,"x":0,"y":0,"curve":"stepped"},{"time":2.5333,"x":172,"y":167,"curve":[0.25,0,0.75,1]},{"time":2.8667,"x":172,"y":-163}]},"15":{"translate":[{"time":0,"x":-1,"y":0}],"scale":[{"time":0,"x":1,"y":1,"curve":"stepped"},{"time":0.7667,"x":1,"y":1,"curve":[0.25,0,0.346,0.99]},{"time":1,"x":1.5,"y":1.5,"curve":[0.25,0,0.33,0.99]},{"time":1.3,"x":1,"y":1}]},"root":{"translate":[{"time":0,"x":0,"y":0}]},"11":{"translate":[{"time":0,"x":-348.08,"y":167,"curve":[0.25,0,0.75,1]},{"time":0.3333,"x":-1.9,"y":2.13,"curve":"stepped"},{"time":2,"x":-348.08,"y":167,"curve":[0.25,0,0.75,1]},{"time":2.3333,"x":172,"y":-163}]},"coin_4":{"translate":[{"time":0,"x":-240,"y":128.75}]},"12":{"translate":[{"time":0,"x":1.92,"y":0}]},"spin":{"translate":[{"time":0,"x":-110,"y":323},{"time":1.1667,"x":-110,"y":323.96},{"time":1.6,"x":-110,"y":-1522.9,"curve":[0.25,0,0.459,1]},{"time":1.8,"x":-110,"y":-1484.62}]},"coin_5":{"translate":[{"time":0,"x":-257.27,"y":1024.91}]},"55":{"translate":[{"time":0,"x":14.74,"y":0}]},"coin_6":{"translate":[{"time":0,"x":-240,"y":713.17}]},"coin_7":{"translate":[{"time":0,"x":-252.95,"y":426.58}]},"56":{"translate":[{"time":0,"x":14.74,"y":0}]},"13":{"translate":[{"time":0,"x":-244,"y":1324.91,"curve":"stepped"},{"time":2.1333,"x":-244,"y":1324.91,"curve":[0.25,0,0.542,1]},{"time":2.4667,"x":282,"y":1321.62}]},"14":{"translate":[{"time":0,"x":-244,"y":1481.7,"curve":"stepped"},{"time":2.0667,"x":-244,"y":1481.7,"curve":[0.25,0,0.558,1]},{"time":2.4,"x":282,"y":1321.62}]},"coin_10":{"translate":[{"time":0,"x":234.72,"y":-2.14}]},"coin_11":{"translate":[{"time":0,"x":234.72,"y":300.93}]},"bone5":{"translate":[{"time":0,"x":230,"y":1795.64,"curve":"stepped"},{"time":2.6333,"x":230,"y":1795.64,"curve":[0.25,0,0.75,1]},{"time":2.9667,"x":230,"y":1632.7}]},"coin_14":{"translate":[{"time":0,"x":219.07,"y":1330.81}]},"57":{"translate":[{"time":0,"x":14.74,"y":0}]},"coin_15":{"translate":[{"time":0,"x":232.74,"y":1029.56}]},"17":{"translate":[{"time":0,"x":1.92,"y":0}]},"coin_16":{"translate":[{"time":0,"x":232.74,"y":882.87}]},"18":{"translate":[{"time":0,"x":1.92,"y":0}]},"coin_17":{"translate":[{"time":0,"x":219.07,"y":594.52}]},"58":{"translate":[{"time":0,"x":14.74,"y":0}]},"spin_2":{"translate":[{"time":0,"x":-58,"y":363.61,"curve":"stepped"},{"time":1.2333,"x":-58,"y":363.61},{"time":1.6,"x":-58,"y":-1064.46},{"time":1.8,"x":-58,"y":-1804.91,"curve":[0.25,0,0.362,1]},{"time":2,"x":-58,"y":-1795.7}]},"coin_18":{"translate":[{"time":0,"x":172,"y":167}],"scale":[{"time":0,"x":1,"y":1,"curve":"stepped"},{"time":0.3,"x":1,"y":1,"curve":[0.25,0,0.75,1]},{"time":0.3667,"x":1.06,"y":1.06,"curve":[0.25,0,0.75,1]},{"time":0.4667,"x":1,"y":1,"curve":"stepped"},{"time":2.5,"x":1,"y":1,"curve":[0.25,0,0.75,1]},{"time":2.5667,"x":1.06,"y":1.06,"curve":[0.25,0,0.75,1]},{"time":2.6667,"x":1,"y":1}]},"coin_19":{"translate":[{"time":0,"x":-176,"y":-158.02}],"scale":[{"time":0,"x":1,"y":1,"curve":"stepped"},{"time":0.2,"x":1,"y":1,"curve":[0.25,0,0.75,1]},{"time":0.2667,"x":1.06,"y":1.06,"curve":[0.25,0,0.75,1]},{"time":0.3667,"x":1,"y":1,"curve":"stepped"},{"time":2.2667,"x":1,"y":1,"curve":[0.25,0,0.75,1]},{"time":2.3333,"x":1.06,"y":1.06,"curve":[0.25,0,0.75,1]},{"time":2.4333,"x":1,"y":1}]},"19":{"translate":[{"time":0,"x":1.92,"y":0}]},"coin_20":{"translate":[{"time":0,"x":-350,"y":167}],"scale":[{"time":0,"x":1,"y":1,"curve":[0.25,0,0.75,1]},{"time":0.0667,"x":1.06,"y":1.06,"curve":[0.25,0,0.75,1]},{"time":0.1667,"x":1,"y":1,"curve":"stepped"},{"time":1.9333,"x":1,"y":1,"curve":[0.25,0,0.75,1]},{"time":2,"x":1.06,"y":1.06,"curve":[0.25,0,0.75,1]},{"time":2.1,"x":1,"y":1}]},"20":{"translate":[{"time":0,"x":1.92,"y":0}]},"21":{"translate":[{"time":0,"x":-170.08,"y":167,"curve":"stepped"},{"time":0.1333,"x":-170.08,"y":167,"curve":[0.25,0,0.75,1]},{"time":0.4667,"x":-1.9,"y":2.13,"curve":"stepped"},{"time":2.2,"x":-170.08,"y":167,"curve":[0.25,0,0.75,1]},{"time":2.5333,"x":172,"y":-163}]},"coin_22":{"translate":[{"time":0,"x":-172,"y":167}],"scale":[{"time":0,"x":1,"y":1,"curve":"stepped"},{"time":0.1,"x":1,"y":1,"curve":[0.25,0,0.75,1]},{"time":0.1667,"x":1.06,"y":1.06,"curve":[0.25,0,0.75,1]},{"time":0.2667,"x":1,"y":1,"curve":"stepped"},{"time":2.2,"x":1,"y":1,"curve":[0.25,0,0.75,1]},{"time":2.2667,"x":1.06,"y":1.06,"curve":[0.25,0,0.75,1]},{"time":2.3667,"x":1,"y":1}]},"22":{"translate":[{"time":0,"x":1.92,"y":0}]},"coin_24":{"translate":[{"time":0,"x":346,"y":0}],"scale":[{"time":0,"x":1,"y":1,"curve":"stepped"},{"time":0.4,"x":1,"y":1,"curve":[0.25,0,0.75,1]},{"time":0.4667,"x":1.06,"y":1.06,"curve":[0.25,0,0.75,1]},{"time":0.5667,"x":1,"y":1,"curve":"stepped"},{"time":2.7,"x":1,"y":1,"curve":[0.25,0,0.75,1]},{"time":2.7667,"x":1.06,"y":1.06,"curve":[0.25,0,0.75,1]},{"time":2.8667,"x":1,"y":1}]},"coin_25":{"translate":[{"time":0,"x":-244,"y":1324.91}],"scale":[{"time":0,"x":1,"y":1,"curve":"stepped"},{"time":2.1,"x":1,"y":1,"curve":[0.25,0,0.75,1]},{"time":2.1667,"x":1.06,"y":1.06,"curve":[0.25,0,0.75,1]},{"time":2.2667,"x":1,"y":1}]},"23":{"translate":[{"time":0,"x":1.92,"y":0}]},"coin_26":{"translate":[{"time":0,"x":-244,"y":1481.74}],"scale":[{"time":0,"x":1,"y":1,"curve":"stepped"},{"time":2,"x":1,"y":1,"curve":[0.25,0,0.75,1]},{"time":2.0667,"x":1.06,"y":1.06,"curve":[0.25,0,0.75,1]},{"time":2.1667,"x":1,"y":1}]},"24":{"translate":[{"time":0,"x":1.92,"y":0}]},"coin_27":{"translate":[{"time":0,"x":230,"y":1795.64}],"scale":[{"time":0,"x":1,"y":1,"curve":"stepped"},{"time":2.6,"x":1,"y":1,"curve":[0.25,0,0.75,1]},{"time":2.6667,"x":1.06,"y":1.06,"curve":[0.25,0,0.75,1]},{"time":2.7667,"x":1,"y":1}]},"special_coin2":{"translate":[{"time":0,"x":230.57,"y":1634.1}],"scale":[{"time":0,"x":1,"y":1,"curve":"stepped"},{"time":3.0667,"x":1,"y":1,"curve":[0.25,0,0.346,0.99]},{"time":3.2,"x":1.13,"y":1.13,"curve":[0.25,0,0.33,0.99]},{"time":3.5,"x":1,"y":1}]},"186":{"scale":[{"time":0,"x":1,"y":1,"curve":"stepped"},{"time":3.0667,"x":1,"y":1,"curve":[0.25,0,0.346,0.99]},{"time":3.3,"x":1.5,"y":1.5,"curve":[0.25,0,0.33,0.99]},{"time":3.6,"x":1,"y":1}]},"bone7":{"translate":[{"time":0,"x":346,"y":0,"curve":"stepped"},{"time":0.4333,"x":346,"y":0,"curve":[0.25,0,0.75,1]},{"time":0.7667,"x":0,"y":0,"curve":"stepped"},{"time":2.7333,"x":346,"y":0,"curve":[0.25,0,0.75,1]},{"time":3.0667,"x":172,"y":-163}]},"16":{"translate":[{"time":0,"x":0,"y":0,"curve":"stepped"},{"time":2.4,"x":0,"y":0,"curve":[0.25,0,0.75,1]},{"time":2.7333,"x":172,"y":-163}],"scale":[{"time":0,"x":1,"y":1}]}},"deform":{"default":{"mask":{"mask":[{"time":0,"curve":"stepped"},{"time":1.8,"vertices":[1.27002,-30.48,0.92896,40.87602,2.78696,42.73404,-1.26993,-36.82993]}]}}},"drawOrder":[{"time":0},{"time":1.7,"offsets":[{"slot":"coin20","offset":-36}]},{"time":1.8,"offsets":[{"slot":"coin20","offset":-36},{"slot":"coin18","offset":-38}]}]}}}